tts_webui_extension/riffusion/main.py
tts_webui_extension/riffusion/spectro.py
tts_webui_extension/riffusion/spectro2.py
tts_webui_extension_riffusion-0.0.3.dist-info/licenses/LICENSE
tts_webui_extension_riffusion-0.0.3.dist-info/METADATA
tts_webui_extension_riffusion-0.0.3.dist-info/WHEEL
tts_webui_extension_riffusion-0.0.3.dist-info/top_level.txt
tts_webui_extension_riffusion-0.0.3.dist-info/RECORD
