Metadata-Version: 2.4
Name: tts_webui_extension.riffusion
Version: 0.0.3
Summary: Riffusion allows generating music from text.
Home-page: https://github.com/rsxdalv/tts_webui_extension.riffusion
Author: rsxdalv
Classifier: Programming Language :: Python :: 3
Classifier: License :: OSI Approved :: MIT License
Classifier: Operating System :: OS Independent
License-File: LICENSE
Requires-Dist: pydub
Requires-Dist: scipy
Requires-Dist: diffusers
Requires-Dist: transformers
Requires-Dist: accelerate
Dynamic: author
Dynamic: classifier
Dynamic: home-page
Dynamic: license-file
Dynamic: requires-dist
Dynamic: summary
